azure_devops_mcp/__init__.py
azure_devops_mcp/azure_devops_client.py
azure_devops_mcp/server.py
azure_devops_mcp-0.2.0.dist-info/METADATA
azure_devops_mcp-0.2.0.dist-info/WHEEL
azure_devops_mcp-0.2.0.dist-info/entry_points.txt
azure_devops_mcp-0.2.0.dist-info/RECORD
