Metadata-Version: 2.4
Name: azure-devops-mcp
Version: 0.2.0
Summary: MCP server for Azure DevOps / TFS integration
Project-URL: Homepage, https://github.com/winning/azure-devops-mcp
Project-URL: Repository, https://github.com/winning/azure-devops-mcp
Project-URL: Issues, https://github.com/winning/azure-devops-mcp/issues
Author-email: pth <pth@winning.com.cn>
License: MIT
Keywords: azure-devops,claude,mcp,model-context-protocol,tfs
Classifier: Development Status :: 3 - Alpha
Classifier: Intended Audience :: Developers
Classifier: License :: OSI Approved :: MIT License
Classifier: Programming Language :: Python :: 3
Classifier: Programming Language :: Python :: 3.10
Classifier: Programming Language :: Python :: 3.11
Classifier: Programming Language :: Python :: 3.12
Classifier: Programming Language :: Python :: 3.13
Classifier: Topic :: Software Development
Requires-Python: >=3.10
Requires-Dist: aiohttp>=3.9.0
Requires-Dist: mcp>=0.9.0
Requires-Dist: pydantic>=2.0.0
Requires-Dist: python-dotenv>=1.0.0
Requires-Dist: pyyaml>=6.0.0
